<?xml version="1.0" encoding="utf-8"?>
<TextureAtlas imagePath="spr_gold.png">
	<!-- Created with Adobe Animate version 22.0.8.217 -->
	<!-- http://www.adobe.com/products/animate.html -->
	<SubTexture name="gold0000" x="0" y="0" width="333" height="523" frameX="0" frameY="0" frameWidth="339" frameHeight="523"/>
	<SubTexture name="gold0001" x="0" y="0" width="333" height="523" frameX="0" frameY="0" frameWidth="339" frameHeight="523"/>
	<SubTexture name="gold0002" x="334" y="0" width="333" height="523" frameX="-6" frameY="0" frameWidth="339" frameHeight="523"/>
	<SubTexture name="gold0003" x="334" y="0" width="333" height="523" frameX="-6" frameY="0" frameWidth="339" frameHeight="523"/>
	<SubTexture name="gold0004" x="668" y="0" width="333" height="523" frameX="-3" frameY="0" frameWidth="339" frameHeight="523"/>
	<SubTexture name="gold0005" x="668" y="0" width="333" height="523" frameX="-3" frameY="0" frameWidth="339" frameHeight="523"/>
	<SubTexture name="gold0006" x="668" y="0" width="333" height="523" frameX="-4" frameY="0" frameWidth="339" frameHeight="523"/>
	<SubTexture name="gold0007" x="668" y="0" width="333" height="523" frameX="-4" frameY="0" frameWidth="339" frameHeight="523"/>
</TextureAtlas>
